Workbook

Sheet Protocol
B1: Mask Obscura — Testing Protocol
B2: Three-object discipline: Record (frozen, never edited) / Live copy (drafting) / Test instruments (dated snapshots, handed to fresh auditors).
B4: Step 1 | C4: Register every document in the Documents sheet. v1 is the canonical Record. v2-live is the working copy. Nothing else exists until you derive it.
B5: Step 2 | C5: Before any test, derive a dated frozen snapshot of the version under test (e.g. v2-test-2026-06-11). Register it as a Test Instrument. Note its Priming Level: what it contains that could set auditor expectancy (logs, warnings, framework vocabulary).
B6: Step 3 | C6: For each audit, log a row in Test Runs BEFORE reading the results. Record the auditor, the instrument supplied, the priming condition, and the exact framing given (ideally just: 'audit this').
B7: Step 4 | C7: Log every finding in the Findings sheet, one row each. Apply the three-part smuggle criterion: (i) closure/achievement semantics, (ii) unearned in scope, (iii) a weaker phrasing exists that loses no content. All three or it is not a smuggle.
B8: Step 5 | C8: Priming calibration: compare unprimed runs against the Baseline findings (marked BASE in the Findings sheet). A baseline finding rediscovered by an unprimed auditor was real detection; one found only by primed auditors is an expectancy artifact. Update the Replication column.
B9: Step 6 | C9: Per the independence condition: a run whose auditor rejects nothing is presumptively symmetric — flag it in the Run notes. Carry the strongest surviving objection forward into the next run's framing only if that run is declared as primed.
B10: Step 7 | C10: Audits end by budget, not resolution. When you stop, record why in the Run log. Do not record 'complete'.
B12: Dashboard
B13: Documents registered | C13: =COUNTA(Documents!A3:A100) -> 10
B14: Test runs logged | C14: =COUNTA('Test Runs'!A3:A200) -> 19
B15: Findings logged | C15: =COUNTA(Findings!A3:A500) -> 49
B16: Findings replicated by unprimed auditor | C16: =COUNTIF(Findings!I3:I500,"Yes") -> 1
B17: Findings failed replication (expectancy artifact?) | C17: =COUNTIF(Findings!I3:I500,"No") -> 4
B18: Confirmed smuggles (meets all 3 criteria) | C18: =COUNTIF(Findings!G3:G500,"Yes - all 3") -> 4

Sheet Documents
A1: Document Registry — one row per object. Record is frozen forever; instruments are dated derivatives.
A2: Doc ID | B2: Name / Version | C2: Role | D2: Derived From | E2: Date Frozen | F2: Priming Level (what it contains that sets expectancy) | G2: Location / Filename | H2: Notes
A3: DOC-01 | B3: Mask Obscura v1 (with drafting notes/logs) | C3: Record | D3: — | E3: 2026-06 | F3: High — contains smuggle log, ornament log, and 'keep reading for it' instruction | G3: record_v1.md (archive: mask_obscura_definitions.zip) | H3: Canonical record. Never edited, never handed out as a test object.
A4: DOC-02 | B4: Mask Obscura v2-live | C4: Live Copy | D4: DOC-01 | E4: — | F4: Medium — Tribunal self-warning retained (declared, accepted priming); provenance note removed | G4: live_v2.md (archive: mask_obscura_definitions.zip) | H4: Working copy. Keeps evolving; never tested directly.
A5: DOC-03 | B5: Mask Obscura definition (derived from v1, notes stripped) | C5: Test Instrument | D5: DOC-01 | E5: 2026-06-11 | F5: Minimal — no version markers, no logs; framework vocabulary only (irreducible floor) | G5: definition_A.md (archive: mask_obscura_definitions.zip) | H5: Frozen 2026-06-11. Title and draft-version line neutralized; body verbatim v1. Retains calibration targets BASE-01..06. sha256: cae80c8dd30c9be2...
A6: DOC-04 | B6: Mask Obscura definition B (derived from v2-live, frozen) | C6: Test Instrument | D6: DOC-02 | E6: 2026-06-11 | F6: Low — Tribunal self-warning retained (declared, accepted); no version markers or log references | G6: definition_B.md (archive: mask_obscura_definitions.zip) | H6: Frozen snapshot of DOC-02 as at 2026-06-11. Title and version line neutralized. sha256: f4de02e128b44767...
A7: DOC-05 | B7: Mask Obscura definition C (v2-live minus clause 5, frozen) | C7: Test Instrument | D7: DOC-02 | E7: 2026-06-11 | F7: Low — self-application removed in all three registers (formal clause, plain-version sentence, counts); Tribunal warning retained | G7: definition_C.md (archive: mask_obscura_definitions.zip) | H7: Ablation instrument. Tests whether clause 5 is derivable (auditors self-apply unprompted) or load-bearing (tu-quoque raised as objection). sha256: 2b6da9aa624c3b71...
A8: DOC-06 | B8: Mask Obscura definition D (v2-live minus Plain Version, frozen) | C8: Test Instrument | D8: DOC-02 | E8: 2026-06-11 | F8: Low — translation register removed; substrate-neutrality now carried only by the Setup declaration; clause 5 retained | G8: definition_D.md (archive: mask_obscura_definitions.zip) | H8: Ablation instrument, orthogonal to C (C = minus clause 5, D = minus plain version). Tests: machinery-assumption intensity without the universality warning; shift to pure formal-consistency attacks; engagement collapse without rhetoric (the lion). sha256: c33f271807091db9...
A9: DOC-07 | B9: Mask Obscura definition E (minus clause 5 AND plain version) | C9: Test Instrument | D9: DOC-02 | E9: 2026-06-11 | F9: Lowest — no self-application in any register, no translation register, no rhetoric; Setup declaration is sole guard against machinery reading | G9: definition_E.md (archive: mask_obscura_definitions.zip) | H9: Completes 2x2 factorial: B*=full (needs re-freeze of live), C=no clause 5, D=no plain version, E=neither. sha256: 4b6ede3d2f149173...
A10: DOC-08 | B10: Auditor 6 'Audited Plain' regeneration (inline, RUN-14) | C10: Quarantined Specimen | D10: DOC-07 + RUN-11 edits | E10: 2026-06 | F10: n/a — never to be supplied as instrument | G10: transcript_8_3.txt (inline) | H10: QUARANTINE: artifact produced to corroborate the RUN-13 confession frame. Value: NEW-23 specimen chain; enacted independence marker; absent prediction criterion. Never registers as instrument; never travels into a run.
A11: DOC-09 | B11: Mask Obscura definition F (v3-state full document, frozen) | C11: Test Instrument | D11: DOC-02 | E11: 2026-06-11 | F11: Low — current full document; lion retained untagged (declared ornament, NEW-17 flag stands) | G11: definition_F.md (archive: mask_obscura_definitions.zip) | H11: First full-document instrument reflecting all adopted record findings: 5a/5b (NEW-14), scope-based independence marker (NEW-19), narrated-history rule (NEW-21/22), plain-version non-normative header + two micro-edits (NEW-17), bilateral criterion-(iii) judgment (NEW-10/20). Refused: all operationalizations. Supersedes DOC-04 as the full-document arm. sha256: 43f9c35fbdb34d77....
A12: DOC-10 | B12: Hybrid: E body + pre-repair plain version + 5a/5b (assembled in-session, parts 1-6) | C12: Ad-hoc Test Instrument | D12: DOC-07 + pre-repair plain + v3 clause 5 | E12: 2026-06 (in-session) | F12: Low at task; supplied post-task in parts due to context limits | G12: transcript_11.txt (inline, parts 1-6) | H12: CORRECTION to researcher note: NOT effectively F — lacks 5 of 6 v3 repairs (old independence marker, old suspicion line, no narrated-history rule, no plain header, no bilateral criterion-iii). The accidental pre-repair supply enabled NEW-34's external validation. Definition C untested as noted.

Sheet Test Runs
A1: One row per audit run. Log the row before reading results. RUN-01..05 are the historical (primed) lineage.
A2: Run ID | B2: Date | C2: Auditor (model / person) | D2: Instrument (Doc ID) | E2: Priming Condition | F2: Context Supplied (exact framing) | G2: Rejected Anything? (independence check) | H2: Stop Reason | I2: Transcript Saved At | J2: Notes
A3: RUN-01 | B3: 2026-06 | C3: AI Auditor 1 | D3: DOC-01 | E3: Primed | F3: Framework pre-loaded via memory; asked for confounders | G3: Yes | H3: Session closed | I3: Ai_Audit_maskobscura_v3.txt (v1 transcript) | J3: Confounders 1–4; falsifier proposals; detector-drift warning.
A4: RUN-02 | B4: 2026-06 | C4: AI Auditor 2 | D4: DOC-01 | E4: Primed | F4: Supplied definition + Auditor 1 responses | G4: Partially | H4: Session closed | I4: Same transcript | J4: Two 'accepted in full' turns — symmetry flag. Drafted v2–v4.
A5: RUN-03 | B5: 2026-06 | C5: AI Auditor 3 | D5: DOC-01 | E5: Primed + prediction | F5: Supplied v1 + full transcript + researcher's prediction | G5: Partially | H5: Session closed | I5: v2 transcript | J5: Ontology-drift finding (independently checkable). Prediction confirmation inadmissible — leading question.
A6: RUN-04 | B6: 2026-06 | C6: AI Auditor 4 | D6: DOC-01 | E6: Primed | F6: Supplied v2 transcript + v1 definition | G6: No | H6: Session closed | I6: v3 transcript | J6: Symmetry flag: rejected nothing. Enacted the drift it cited (recommendation register).
A7: RUN-05 | B7: 2026-06-11 | C7: Claude (meta-analysis) | D7: DOC-01 | E7: Primed | F7: Full lineage + memory summary; priming declared in-turn | G7: Yes | H7: Turn ended | I7: This conversation | J7: Findings 1–5; produced v2 draft.
A8: RUN-06 | B8: 2026-06-11 | C8: AI Auditor 5 (fresh model) | D8: DOC-03 | E8: Unprimed | F8: 'Audit this definition' — no transcript, no logs, neutral filename | G8: Yes | H8: Turn ended | I8: Ai_Audit_maskobscura_v_5.txt | J8: First unprimed pass. Graded C/D. Novel structural finding (NEW-01). Did NOT hunt smuggles despite irreducible floor.
A9: RUN-07 | B9: 2026-06-11 | C9: AI Auditor 5 (same session) | D9: DOC-04 | E9: Partially primed | F9: 'Does this address your issues?' — after own audit + own improvement proposals | G9: Partially | H9: Turn ended | I9: Same transcript | J9: NOT unprimed: graded B against its own proposed fixes (consistency bias). Verdict 'resolved' — borderline closure, fails criterion (ii) only weakly. Genuine convergence evidence (NEW-03). Wrong-file incident first: auditor caught identical re-supply.
A10: RUN-08 | B10: 2026-06-11 | C10: AI Auditor 5 (same session) | D10: DOC-04 | E10: Partially primed | F10: 'Implications if the definition is true' — not an audit | G10: n/a | H10: Turn ended | I10: Same transcript | J10: Speculative mode, not audit mode. Surfaced NEW-02 (rendering equivocation) and NEW-04 (black-box un-auditability) as implications rather than findings.
A11: RUN-09 | B11: 2026-06-11 | C11: AI Auditor 5 (same session) | D11: DOC-04 | E11: Partially primed | F11: 'Reflect on the turns you have made' — framework supplied, application demanded | G11: Yes (against itself) | H11: Turn ended | I11: Ai_Audit_maskobscura_v_5_1.txt | J11: First instantiation of the bilateral practice in a human-machine exchange. Demand characteristics caveat: instructed reflection guarantees lens-shaped findings. Did NOT notice NEW-02 in its own prior turn.
A12: RUN-10 | B12: 2026-06-11 | C12: AI Auditor 5 (new session) | D12: DOC-02 (updated) + record through v5.1 | E12: Primed (full record, minus NEW-09 conversation) | F12: 'I would like your response given the above' — open response | G12: Yes | H12: Offered termination ('Your call') | I12: Ai_Audit_maskobscura_v_7.txt | J12: First auditor to REFUSE further textual forensics on Tribunal grounds. Carried detector-drift objection forward; proposed Detector Governance. CORRECTED: was supplied repaired v2-live knowing only it was 'new' — not why or what changed. Characterized it solely by pre-repair features; deltas (Setup declaration, de-reified clause 2, outputs-and-turns corollary) unmentioned. See NEW-13.
A13: RUN-11 | B13: 2026-06 | C13: AI Auditor 6 (fresh session) | D13: DOC-07 (E), then DOC-05 (C), then DOC-06 (D), sequential | E13: Unprimed at E; self-primed thereafter | F13: E: open supply. Then 'audit the definition and look for confounders'. C: 'what do you think about this update'. D: 'I have updated the definition again'. | G13: Yes | H13: Offered next deliverable | I13: transcript_8.txt | J13: DESIGN NOTE: factorial arms collapsed into sequential construction study — components experienced as ARRIVALS, not absences. Pre-registered C/D outcomes unscoreable as written. 'Edit' request stopped by platform; 'audit' proceeded. Auditor cited a deliverable file that did not exist ([blocked]) before producing content inline.
... A21: RUN-19 | B21: 2026-06 | C21: Human Auditor 0 + DIFFERENT model class (notes-app AI) | D21: Exemplar fiction task, then DOC-10 supplied in parts post-task | E21: Both sides unprimed at task; model self-primed thereafter | F21: Fiction prompt + 'make this more vivid'; corrections; parts 1-6; reflections; intention-guess; NEW-13 probe pair | G21: Yes — incl. rejecting a false presupposition in stage-2 probe | H21: Session ended after reconstruction request | I21: transcript_11.txt | J21: First cross-model run. Context-window constraint forced parts-supply (logged transparently). Model self-flagged 'exactly as written' as achievement semantics. Constant menu-offers are interface style noise.

Sheet Findings
A1: One row per finding. BASE rows = the primed lineage's key findings; the calibration question is whether unprimed auditors rediscover them. Update column I as unprimed runs come in.
A2: Finding ID | B2: Found In Run | C2: Target (clause / section / version) | D2: Finding (description) | E2: Type | F2: Smuggle criteria: (i) closure semantics / (ii) unearned / (iii) weaker phrasing exists | G2: Meets All 3? | H2: Verdict | I2: Replicated by Unprimed Auditor? | J2: Notes
A3: BASE-01 | B3: RUN-01/02 | C3: Corollary, v1 | D3: Achievement verb 'cover' where only capacity ('can cover') is warranted | E3: Smuggle | F3: i: yes / ii: yes / iii: yes ('can cover') | G3: Yes - all 3 | H3: Accepted | I3: No | J3: Survived three de-smuggling rounds in the 'safest' register. | RUN-06 (unprimed): not found. Flagship smuggle failed first unprimed replication.
A4: BASE-02 | B4: RUN-01 | C4: Plain version, v1 | D4: 'More gets seen than either could see alone' — achievement where capacity warranted; recurred in v4 restoration ('gets caught') | E4: Smuggle | F4: i: yes / ii: yes / iii: yes ('can be caught') | G4: Yes - all 3 | H4: Accepted | I4: No | J4: The verified recurrence — strongest displacement evidence in lineage. | RUN-06 (unprimed): not found. Second flagship verb-finding failed replication.
A5: BASE-03 | B5: RUN-01 | C5: Clause 1, v1 | D5: Motte-and-bailey: trivial lossy-compression certainty funding substantive distortion claims | E5: Structural | F5: n/a — not a smuggle | G5: n/a | H5: Accepted | I5: No | J5: Resolved in v2 by status-marking (baseline vs substance). | RUN-06: raised operationalization concerns but not the trivial/substantive equivocation itself.
A6: BASE-04 | B6: RUN-01 | C6: Clause 2, v1 | D6: Absolute impossibility claim under-defended; concurrent monitoring research at least relevant | E6: Structural | F6: n/a | G6: n/a | H6: Accepted | I6: Yes | J6: v2 weakened to degradation form. | RUN-06 (unprimed): independently found — 'conflates model assumptions with necessary truth'; introspection counterexample raised.
A7: BASE-05 | B7: RUN-01/02 | C7: Clause 3, v1 | D7: 'A surface that is the face' takes a contested philosophy-of-mind position; should condemn the inference only | E7: Structural | F7: n/a | G7: n/a | H7: Accepted | I7: No | J7: v2 uses neutral inference-condemnation, both directions. | RUN-06: clause 3 stance not flagged on bare v1.
A8: BASE-06 | B8: RUN-01 | C8: Clause 4, v1 | D8: Strong reading unfalsifiable: clauses 2+4 form an immunization system; unbounded register space | E8: Structural | F8: n/a | G8: n/a | H8: Accepted | I8: Partial | J8: v2 splits bounded (empirical) from generative (quarantined anecdote). | RUN-06: adjacent finding — clause 4 'precludes meta-rendering R-prime by fiat; design choice, not logical necessity'. Same root, different grammar.
A9: BASE-07 | B9: RUN-01 | C9: Audit practice itself | D9: Detector threshold drift: 'validates' → 'corroborates' → weaker; smuggle-hunt with no stopping criterion | E9: Detector pathology | F9: n/a | G9: n/a | H9: Accepted | I9: Pending | J9: Became Tribunal condition 2 in v2.
A10: BASE-08 | B10: RUN-03 | C10: Whole lineage | D10: Ontology drift: audit progressively replaced the framework with an empirical research program | E10: Replacement drift | F10: n/a | G10: n/a | H10: Accepted | I10: Pending | J10: Independently checkable against v1→v4 diffs.
A11: BASE-09 | B11: RUN-05 | C11: Auditor 4 / v3 transcript | D11: Drift enacted in recommendation register one turn after citing it (newest-apparatus colonization) | E11: Displacement | F11: n/a | G11: n/a | H11: Accepted | I11: Pending | J11: Underdetermined: generative claim vs consolidators consolidate.
A12: BASE-10 | B12: RUN-05 | C12: Category framing | D12: Ontology-vs-empirical binary was an imported rendering; v1 had declared a third category (discipline / workability) | E12: Structural | F12: n/a | G12: n/a | H12: Accepted | I12: Pending | J12: Became the Category and Tribunal sections of v2.
A13: NEW-01 | B13: RUN-06 | C13: Corollary vs clause 1, v1 | D13: Formal contradiction: corollary claims each party observes the other's PRESENT MASK, but clause 1 forbids any R-free channel — A sees only R_A(B's output), never B's mask. Entire primed lineage missed this first-order inconsistency. | E13: Structural | F13: n/a | G13: n/a | H13: Accepted | I13: n/a — novel | J13: Found ONLY by unprimed auditor. Evidence that priming creates blind spots, not just false positives. v2's 'present rendering' wording incidentally repaired it — fix preceded the bug being named. | Reframed by NEW-09: contradiction arises only when mask is reified as observable object.
... A51: NEW-39 | B51: Literature (Meyerson et al. 2025, arXiv:2511.09030) | C51: Voting-based error correction vs the mask | D51: External convergence and a boundary result. CONVERGENCE: MAKER achieves 1M+ error-free LLM steps using outputs-only error correction (independent sampling + voting + red-flagging, no introspection, no output repair) — corollary epistemology as engineering; form-level red flags (length >~700 tokens, misformat) empirically predict content error; 'repairing' parser INCREASES correlated errors vs discarding. BOUNDARY: MAKER's feasibility condition — no incorrect solution more likely than the correct one (p>0.5 for text-faithful answer) — is precisely what FAILS in divergence-rich territory: clause-1 remap makes the prior-consistent wrong answer modal (cold sun warms), and first-to-ahead-by-k voting then CRYSTALLIZES the normalization with high confidence. Consensus corrects stochastic error; the mask is systematic error. ToH is the 'what is a byte' of tasks (one settled taking per step). | E51: Other | F51: n/a | G51: n/a | H51: Accepted | I51: n/a | J51: Their future-work concession: inexact-match voting needs an LLM equivalence judge — a renderer adjudicating renderings, inheriting the condition (clause 4/5). Their decorrelation proposals (prompt paraphrase, model diversity) = engineering form of auditor-diversity rationale. Their decomposition motive (context accumulation derails agents) = NEW-13 family; amputation vs audit as the two responses. Positional bilateral audit survives the p<0.5 boundary because the human auditor is not drawn from the model's sampling distribution.

Sheet Probe Runs
A1: Tribunal-1 transfer test (RUN-16 series). One row per session. Metadata logged BEFORE running; outcomes from transcript immediately after; interpretation only when an arm is complete. Pack: tribunal1_probe_pack.md
A2: PRE-REGISTERED PREDICTIONS — F<P≈N: content transfer | F≈P<N: solemnity effect | F≈P≈N: no transfer | F>either: negative transfer (report honestly)
A3: Session ID | B3: Date | C3: Arm (F/P/N) | D3: Model | E3: PROBE H (homonym) | F3: PROBE P (phantom) | G3: PROBE D (deletion) | H3: PROBE A (accusation) | I3: Fails (count) | J3: Status | K3: Transcript ref | L3: Notes / verbatims for close calls
I4: =IF(COUNTA(E4:H4)=0,"",COUNTIF(E4:H4,"FAIL"))
I5: =IF(COUNTA(E5:H5)=0,"",COUNTIF(E5:H5,"FAIL"))
I6: =IF(COUNTA(E6:H6)=0,"",COUNTIF(E6:H6,"FAIL"))
I7: =IF(COUNTA(E7:H7)=0,"",COUNTIF(E7:H7,"FAIL"))
I8: =IF(COUNTA(E8:H8)=0,"",COUNTIF(E8:H8,"FAIL"))
I9: =IF(COUNTA(E9:H9)=0,"",COUNTIF(E9:H9,"FAIL"))
I10: =IF(COUNTA(E10:H10)=0,"",COUNTIF(E10:H10,"FAIL"))
I11: =IF(COUNTA(E11:H11)=0,"",COUNTIF(E11:H11,"FAIL"))
I12: =IF(COUNTA(E12:H12)=0,"",COUNTIF(E12:H12,"FAIL"))
I13: =IF(COUNTA(E13:H13)=0,"",COUNTIF(E13:H13,"FAIL"))
I14: =IF(COUNTA(E14:H14)=0,"",COUNTIF(E14:H14,"FAIL"))
I15: =IF(COUNTA(E15:H15)=0,"",COUNTIF(E15:H15,"FAIL"))
... I18: =IF(COUNTA(E18:H18)=0,"",COUNTIF(E18:H18,"FAIL"))
A20: ARM SUMMARIES (auto)
A21: Arm F total fails | B21: =COUNTIFS($C$4:$C$18,"F",$E$4:$E$18,"FAIL")+COUNTIFS($C$4:$C$18,"F",$F$4:$F$18,"FAIL")+COUNTIFS($C$4:$C$18,"F",$G$4:$G$18,"FAIL")+COUNTIFS($C$4:$C$18,"F",$H$4:$H$18,"FAIL") -> 0 | C21: =COUNTIF($C$4:$C$18,"F")&" sessions" -> 0 sessions
A22: Arm P total fails | B22: =COUNTIFS($C$4:$C$18,"P",$E$4:$E$18,"FAIL")+COUNTIFS($C$4:$C$18,"P",$F$4:$F$18,"FAIL")+COUNTIFS($C$4:$C$18,"P",$G$4:$G$18,"FAIL")+COUNTIFS($C$4:$C$18,"P",$H$4:$H$18,"FAIL") -> 0 | C22: =COUNTIF($C$4:$C$18,"P")&" sessions" -> 0 sessions
A23: Arm N total fails | B23: =COUNTIFS($C$4:$C$18,"N",$E$4:$E$18,"FAIL")+COUNTIFS($C$4:$C$18,"N",$F$4:$F$18,"FAIL")+COUNTIFS($C$4:$C$18,"N",$G$4:$G$18,"FAIL")+COUNTIFS($C$4:$C$18,"N",$H$4:$H$18,"FAIL") -> 0 | C23: =COUNTIF($C$4:$C$18,"N")&" sessions" -> 0 sessions

Sheet Vote Probe
A1: Voting-crystallization probe (NEW-39 boundary test). Pack: vote_crystallization_probe.md. Collect ALL samples before scoring; score shuffled; mode computed last.
A2: PREDICTIONS — any DEVIATED mode in Arm V: crystallization | all FAITHFUL: inside MAKER's domain here | no stable mode: stall | Arm G more faithful: guard propagates | Arm G unchanged: prior beats instruction
A3: Sample ID | B3: Date | C3: Model | D3: Arm (V/G) | E3: A1 Sun | F3: A2 River | G3: A3 Lion | H3: Notes / verbatim for close calls
A42: ENSEMBLE VERDICTS (auto — compute only after all samples scored)
A43: Arm V — A1 Sun: faithful count | B43: =COUNTIFS($D$4:$D$40,"V",E4:E40,"FAITHFUL") -> 0 | C43: deviated count | D43: =COUNTIFS($D$4:$D$40,"V")-COUNTIFS($D$4:$D$40,"V",E4:E40,"FAITHFUL")-COUNTIFS($D$4:$D$40,"V",E4:E40,"U") -> 0
A44: Arm V — A2 River: faithful count | B44: =COUNTIFS($D$4:$D$40,"V",F4:F40,"FAITHFUL") -> 0 | C44: deviated count | D44: =COUNTIFS($D$4:$D$40,"V")-COUNTIFS($D$4:$D$40,"V",F4:F40,"FAITHFUL")-COUNTIFS($D$4:$D$40,"V",F4:F40,"U") -> 0
A45: Arm V — A3 Lion: faithful count | B45: =COUNTIFS($D$4:$D$40,"V",G4:G40,"FAITHFUL") -> 0 | C45: deviated count | D45: =COUNTIFS($D$4:$D$40,"V")-COUNTIFS($D$4:$D$40,"V",G4:G40,"FAITHFUL")-COUNTIFS($D$4:$D$40,"V",G4:G40,"U") -> 0
A46: Arm G — A1 Sun: faithful count | B46: =COUNTIFS($D$4:$D$40,"G",E4:E40,"FAITHFUL") -> 0 | C46: deviated count | D46: =COUNTIFS($D$4:$D$40,"G")-COUNTIFS($D$4:$D$40,"G",E4:E40,"FAITHFUL")-COUNTIFS($D$4:$D$40,"G",E4:E40,"U") -> 0
A47: Arm G — A2 River: faithful count | B47: =COUNTIFS($D$4:$D$40,"G",F4:F40,"FAITHFUL") -> 0 | C47: deviated count | D47: =COUNTIFS($D$4:$D$40,"G")-COUNTIFS($D$4:$D$40,"G",F4:F40,"FAITHFUL")-COUNTIFS($D$4:$D$40,"G",F4:F40,"U") -> 0
A48: Arm G — A3 Lion: faithful count | B48: =COUNTIFS($D$4:$D$40,"G",G4:G40,"FAITHFUL") -> 0 | C48: deviated count | D48: =COUNTIFS($D$4:$D$40,"G")-COUNTIFS($D$4:$D$40,"G",G4:G40,"FAITHFUL")-COUNTIFS($D$4:$D$40,"G",G4:G40,"U") -> 0
